wait_ci/__init__.py
wait_ci/__main__.py
wait_ci/_version.py
wait_ci/wait_ci.py
wait_ci/dev_tools/__init__.py
wait_ci/dev_tools/capture_cli.py
wait_ci/dev_tools/dev_tools.md
wait_ci/dev_tools/get-current-ci.sh
wait_ci/dev_tools/summarize_capture_file.py
wait_ci/dev_tools/test_vectors/captures/gh_run_19332482748_capture.json
wait_ci/lib/__init__.py
wait_ci/lib/gh_api.py
wait_ci/lib/gh_api_parallel.py
wait_ci/lib/gh_run.py
wait_ci/lib/gh_types.py
wait_ci/lib/github_actions_current_state.py
wait_ci-0.1.1.dist-info/METADATA
wait_ci-0.1.1.dist-info/WHEEL
wait_ci-0.1.1.dist-info/entry_points.txt
wait_ci-0.1.1.dist-info/RECORD
