Metadata-Version: 2.4
Name: wait-ci
Version: 0.1.1
Summary: CLI tool for waiting on CI pipeline completion
Project-URL: homepage, https://github.com/mikegoelzer/wait-ci
Project-URL: repository, https://github.com/mikegoelzer/wait-ci
Project-URL: documentation, https://github.com/mikegoelzer/wait-ci/readme.md
Project-URL: issues, https://github.com/mikegoelzer/wait-ci/issues
Author: Mike Goelzer
License: MIT
Classifier: Programming Language :: Python :: 3 :: Only
Requires-Python: >=3.10
Requires-Dist: curvpyutils>=0.0.51
Requires-Dist: rich>=13
Provides-Extra: dev
Requires-Dist: pytest>=7.4; extra == 'dev'
